clickhouse_s3_etl_tools/__init__.py
clickhouse_s3_etl_tools/logger.py
clickhouse_s3_etl_tools/configs/__init__.py
clickhouse_s3_etl_tools/configs/config_module.py
clickhouse_s3_etl_tools/connectors/__init__.py
clickhouse_s3_etl_tools/connectors/clickhouse_connector.py
clickhouse_s3_etl_tools/connectors/my_clickhouse_balanced.py
clickhouse_s3_etl_tools/connectors/s3_connector.py
clickhouse_s3_etl_tools/exceptions/__init__.py
clickhouse_s3_etl_tools/exceptions/exception.py
clickhouse_s3_etl_tools/s3_clickhouse_loader/__init__.py
clickhouse_s3_etl_tools/s3_clickhouse_loader/config_module.py
clickhouse_s3_etl_tools/s3_exporter/__init__.py
clickhouse_s3_etl_tools/s3_exporter/__main__.py
clickhouse_s3_etl_tools/s3_exporter/config_module.py
clickhouse_s3_etl_tools/s3_exporter/s3_exporter.py
clickhouse_s3_etl_tools/s3_to_clickhouse_transfer/__init__.py
clickhouse_s3_etl_tools/s3_to_clickhouse_transfer/__main__.py
clickhouse_s3_etl_tools/s3_to_clickhouse_transfer/config_module.py
clickhouse_s3_etl_tools/s3_to_clickhouse_transfer/s3_to_clickhouse_transfer.py
clickhouse_s3_etl_tools/schema/__init__.py
clickhouse_s3_etl_tools/schema/schema_configs.py
clickhouse_s3_etl_tools/schema/schema_dependency_tree.py
clickhouse_s3_etl_tools/schema/schema_table_metadata.py
clickhouse_s3_etl_tools/table_task_tree/__init__.py
clickhouse_s3_etl_tools/table_task_tree/__main__.py
clickhouse_s3_etl_tools/table_task_tree/clickhouse_dependency_tree_builder.py
clickhouse_s3_etl_tools/table_task_tree/config_module.py
clickhouse_s3_etl_tools/table_task_tree/tree_drawer.py
clickhouse_s3_etl_tools/utils/__init__.py
clickhouse_s3_etl_tools/utils/utils.py
clickhouse_s3_etl_tools-0.3.9.dist-info/METADATA
clickhouse_s3_etl_tools-0.3.9.dist-info/WHEEL
clickhouse_s3_etl_tools-0.3.9.dist-info/entry_points.txt
clickhouse_s3_etl_tools-0.3.9.dist-info/top_level.txt
clickhouse_s3_etl_tools-0.3.9.dist-info/RECORD
