Metadata-Version: 2.2
Name: clickhouse-s3-etl-tools
Version: 0.3.9
Summary: clickhouse-s3-etl-tools is a powerful utility designed for seamless data transfers between ClickHouse clusters using the flexibility of Amazon S3 or any S3-compatible storage as an intermediate staging area.
Author: Dmitry Utiralov
Author-email: d.utiralov@netology.tech
Requires-Python: >=3.9
Requires-Dist: sqlparse==0.4.4
Requires-Dist: pydantic==2.5.3
Requires-Dist: clickhouse_driver==0.2.6
Requires-Dist: boto3==1.34.18
Provides-Extra: dev
Requires-Dist: pylint==3.0.3; extra == "dev"
Requires-Dist: pytest==7.4.4; extra == "dev"
Requires-Dist: pytest-dependency==0.6.0; extra == "dev"
Requires-Dist: python-dotenv==1.0.0; extra == "dev"
Requires-Dist: anytree==2.12.1; extra == "dev"
Dynamic: author
Dynamic: author-email
Dynamic: description
Dynamic: description-content-type
Dynamic: provides-extra
Dynamic: requires-dist
Dynamic: requires-python
Dynamic: summary
